bottle_request
