Metadata-Version: 1.0
Name: bottle-request
Version: 0.2.0
Summary: Plugin to give bottle a 'stateless' request object
Home-page: http://github.com/turtlebender/bottle-request/
Author: Tom Howe
Author-email: turtlebender@gmail.com
License: MIT
Platform: any
Classifier: Environment :: Web Environment
Classifier: Intended Audience :: Developers
Classifier: License :: OSI Approved :: MIT License
Classifier: Operating System :: OS Independent
Classifier: Programming Language :: Python
Classifier: Topic :: Internet :: WWW/HTTP :: Dynamic Content
Classifier: Topic :: Software Development :: Libraries :: Python Modules
